{"name":"[TR] NetroX JailBreak Server ~ !ws , !kf , !gloves , !rulet , !","map":"awp_lego_2","password":false,"raw":{"protocol":17,"folder":"csgo","game":"Hosties/Jailbreak v2","steamappid":730,"numplayers":15,"numbots":0,"listentype":"d","environment":"l","secure":0,"version":"1.37.0.9","port":27015,"steamid":"85568392922689708","tags":"128tick,awp,bunny,deathmatch,deathrun,dm,jailbreak,jb,market,mg,prooyun,surf,tr,turkey,insecure","gameid":"730"},"maxplayers":40,"players":[{"name":"cnmbn(ELPATRON)","score":4,"time":201.10470581054688},{"name":"CrawLeSS™","score":3,"time":201.104248046875},{"name":"ASLAN","score":8,"time":201.10325622558594},{"name":"MİSS","score":7,"time":201.10284423828125},{"name":"✪Pafuli","score":10,"time":201.1024169921875},{"name":"Calwin","score":0,"time":201.0838623046875},{"name":"IDeadShotX","score":4,"time":201.08335876464844},{"name":"KatanaTV ツ","score":0,"time":201.0829620361328},{"name":"ayberk) jb.netroxclan.com","score":6,"time":201.0825653076172},{"name":"JustHoldMe!!!","score":13,"time":201.0821533203125},{"name":"TheBestRecep","score":0,"time":201.05264282226562},{"name":"AK_47BEST","score":0,"time":200.24351501464844}],"bots":[],"query":{"host":"jb.netroxclan.com","address":"185.193.165.189","port":27015,"port_query":27015,"type":"csgo","name":"Counter-Strike: Global Offensive"}}